ruru/__init__.py
ruru/_version.py
ruru/config.py
ruru/base/__init__.py
ruru/base/matching.py
ruru/cli/__init__.py
ruru/cli/elements.py
ruru/cli/styles.py
ruru/cli/symbols.py
ruru/cli/themes.py
ruru-0.3.3.dist-info/METADATA
ruru-0.3.3.dist-info/WHEEL
ruru-0.3.3.dist-info/licenses/LICENSE
ruru-0.3.3.dist-info/RECORD
