Metadata-Version: 2.4
Name: ruru
Version: 0.3.3
Summary: A collection of Python utilities ported from the R ecosystem.
Project-URL: Source Code, https://github.com/tonkintaylor/ruru
Project-URL: Bug Tracker, https://github.com/tonkintaylor/ruru/issues
Project-URL: Releases, https://github.com/tonkintaylor/ruru/releases
Project-URL: Source Archive, https://github.com/tonkintaylor/ruru/archive/2c817acf99cbd003f3f34f80029e51dfcfeaf3ee.zip
Author-email: Harel Lustiger <hlustiger@tonkintaylor.co.nz>, Nathan McDougall <nmcdougall@tonkintaylor.co.nz>
Maintainer-email: Data + Analytics <Sub-DisciplineData+AnalyticsStaff@tonkintaylor.co.nz>
License-Expression: MIT
License-File: LICENSE
Classifier: Programming Language :: Python :: 3 :: Only
Classifier: Programming Language :: Python :: 3.10
Classifier: Programming Language :: Python :: 3.11
Classifier: Programming Language :: Python :: 3.12
Classifier: Programming Language :: Python :: 3.13
Requires-Python: >=3.10
Requires-Dist: pydantic>=2.0.0
Requires-Dist: pyyaml>=6.0.2
